man/man1/remotex.1
remotex/__init__.py
remotex/audit.py
remotex/cli.py
remotex/config.py
remotex/exit_codes.py
remotex/history.py
remotex/install_man_pages.py
remotex/performance.py
remotex/profiling.py
remotex/retry.py
remotex/ssh_client.py
remotex/ssh_config.py
remotex/utils.py
remotex/commands/__init__.py
remotex/commands/alias_management.py
remotex/commands/bulk_operations.py
remotex/commands/config_command.py
remotex/commands/connect_command.py
remotex/commands/exec_command.py
remotex/commands/file_transfer.py
remotex/commands/group_management.py
remotex/commands/history_command.py
remotex/commands/profiling_command.py
remotex/commands/quick_commands.py
remotex/commands/server_management.py
remotex/commands/tunnel_command.py
remotex-1.0.1.dist-info/licenses/LICENSE
remotex-1.0.1.dist-info/METADATA
remotex-1.0.1.dist-info/WHEEL
remotex-1.0.1.dist-info/entry_points.txt
remotex-1.0.1.dist-info/top_level.txt
remotex-1.0.1.dist-info/RECORD
