Metadata-Version: 2.4
Name: remotex
Version: 1.0.1
Summary: A feature-rich SSH server management CLI tool
Author-email: Sagar Memane <sagarmemane135@gmail.com>
Maintainer-email: Sagar Memane <sagarmemane135@gmail.com>
License: MIT
Project-URL: Homepage, https://github.com/sagarmemane135/remotex
Project-URL: Repository, https://github.com/sagarmemane135/remotex
Project-URL: Documentation, https://github.com/sagarmemane135/remotex/blob/main/README.md
Project-URL: Issues, https://github.com/sagarmemane135/remotex/issues
Keywords: ssh,server,management,cli,remote
Classifier: Development Status :: 4 - Beta
Classifier: Intended Audience :: Developers
Classifier: Intended Audience :: System Administrators
Classifier: License :: OSI Approved :: MIT License
Classifier: Operating System :: OS Independent
Classifier: Operating System :: POSIX :: Linux
Classifier: Operating System :: MacOS
Classifier: Operating System :: Microsoft :: Windows
Classifier: Programming Language :: Python :: 3
Classifier: Programming Language :: Python :: 3.8
Classifier: Programming Language :: Python :: 3.9
Classifier: Programming Language :: Python :: 3.10
Classifier: Programming Language :: Python :: 3.11
Classifier: Programming Language :: Python :: 3.12
Classifier: Programming Language :: Python :: 3.13
Classifier: Topic :: System :: Systems Administration
Classifier: Topic :: System :: Networking
Classifier: Topic :: Utilities
Classifier: Environment :: Console
Classifier: Natural Language :: English
Requires-Python: >=3.8
License-File: LICENSE
Requires-Dist: typer>=0.12.0
Requires-Dist: paramiko>=3.4.0
Requires-Dist: rich>=13.7.0
Dynamic: license-file
